{
    "type": "FeatureCollection",
    "features": [
        {
            "type": "Feature",
            "geometry": {
                "type": "Polygon",
                "coordinates": [
                    [
                        [
                            -94.45764267204055,
                            30.203156815182524
                        ],
                        [
                            -94.45764267204055,
                            31.84761925514806
                        ],
                        [
                            -97.38962996810318,
                            31.84761925514806
                        ],
                        [
                            -97.38962996810318,
                            30.203156815182524
                        ],
                        [
                            -94.45764267204055,
                            30.203156815182524
                        ]
                    ]
                ]
            },
            "properties": {}
        }
    ]
}