{
    "type": "FeatureCollection",
    "features": [
        {
            "type": "Feature",
            "id": 0,
            "geometry": {
                "type": "Polygon",
                "coordinates": [
                    [
                        [
                            -90.41650911338951,
                            29.503328514871555
                        ],
                        [
                            -90.40580153886327,
                            30.006584517604665
                        ],
                        [
                            -90.36297124075833,
                            31.844718144608578
                        ],
                        [
                            -90.28444902756593,
                            34.79287033083233
                        ],
                        [
                            -91.00185652082376,
                            34.81071628837606
                        ],
                        [
                            -92.49377857147937,
                            34.83213143742853
                        ],
                        [
                            -94.44969551827188,
                            34.828562245919784
                        ],
                        [
                            -94.46040309279812,
                            34.528750159185165
                        ],
                        [
                            -96.5947796150279,
                            34.29675271111671
                        ],
                        [
                            -96.5626568914492,
                            33.443715940526545
                        ],
                        [
                            -97.2300957035846,
                            33.41873159996533
                        ],
                        [
                            -97.95821077136867,
                            33.39017806789536
                        ],
                        [
                            -98.77912481838013,
                            33.35448615280791
                        ],
                        [
                            -98.78983239290636,
                            33.42943917449156
                        ],
                        [
                            -98.82552430799382,
                            33.41873159996533
                        ],
                        [
                            -98.76841724385389,
                            32.508587765235234
                        ],
                        [
                            -98.69346422217023,
                            31.40213839752414
                        ],
                        [
                            -97.70836736575649,
                            31.452107078646577
                        ],
                        [
                            -96.66259425369407,
                            31.48066061071654
                        ],
                        [
                            -96.62690233860661,
                            30.70971524482752
                        ],
                        [
                            -96.56622608295794,
                            29.431944684696646
                        ],
                        [
                            -94.94224394647875,
                            29.449790642240373
                        ],
                        [
                            -94.79233790311145,
                            29.449790642240373
                        ],
                        [
                            -94.68883134935783,
                            29.45335983374912
                        ],
                        [
                            -94.57461722107797,
                            29.456929025257864
                        ],
                        [
                            -94.13560666550228,
                            29.442652259222882
                        ],
                        [
                            -94.0428076862749,
                            29.4283754931879
                        ],
                        [
                            -93.97142385609999,
                            29.424806301679155
                        ],
                        [
                            -93.85720972782013,
                            29.424806301679155
                        ],
                        [
                            -93.74656479104902,
                            29.4283754931879
                        ],
                        [
                            -93.62878147126042,
                            29.442652259222882
                        ],
                        [
                            -93.53598249203304,
                            29.464067408275355
                        ],
                        [
                            -93.48244461940186,
                            29.47477498280159
                        ],
                        [
                            -93.41106078922695,
                            29.510466897889046
                        ],
                        [
                            -93.368230491122,
                            29.53902042995901
                        ],
                        [
                            -93.30041585245584,
                            29.57828153655521
                        ],
                        [
                            -93.25401636284215,
                            29.588989111081446
                        ],
                        [
                            -93.18263253266724,
                            29.599696685607682
                        ],
                        [
                            -93.0934027449486,
                            29.599696685607682
                        ],
                        [
                            -92.99703457421248,
                            29.599696685607682
                        ],
                        [
                            -92.93992751007255,
                            29.596127494098937
                        ],
                        [
                            -92.87925125442388,
                            29.5854199195727
                        ],
                        [
                            -92.83642095631893,
                            29.581850728063955
                        ],
                        [
                            -92.79715984972273,
                            29.581850728063955
                        ],
                        [
                            -92.76503712614402,
                            29.581850728063955
                        ],
                        [
                            -92.72934521105657,
                            29.581850728063955
                        ],
                        [
                            -92.69365329596911,
                            29.57828153655521
                        ],
                        [
                            -92.64368461484668,
                            29.564004770520228
                        ],
                        [
                            -92.60085431674173,
                            29.528312855432773
                        ],
                        [
                            -92.56159321014553,
                            29.49975932336281
                        ],
                        [
                            -92.52233210354933,
                            29.47477498280159
                        ],
                        [
                            -92.47593261393564,
                            29.4676365997841
                        ],
                        [
                            -92.41168716677822,
                            29.4676365997841
                        ],
                        [
                            -92.3545801026383,
                            29.4676365997841
                        ],
                        [
                            -92.26178112341091,
                            29.4676365997841
                        ],
                        [
                            -92.1190134630611,
                            29.4676365997841
                        ],
                        [
                            -92.0012301432725,
                            29.46049821676661
                        ],
                        [
                            -91.92627712158884,
                            29.46049821676661
                        ],
                        [
                            -91.84061652537895,
                            29.46049821676661
                        ],
                        [
                            -91.74424835464282,
                            29.446221450731628
                        ],
                        [
                            -91.65501856692418,
                            29.431944684696646
                        ],
                        [
                            -91.59077311976677,
                            29.431944684696646
                        ],
                        [
                            -91.46585141696067,
                            29.431944684696646
                        ],
                        [
                            -91.36948324622455,
                            29.431944684696646
                        ],
                        [
                            -91.14819337268233,
                            29.431944684696646
                        ],
                        [
                            -91.03397924440247,
                            29.431944684696646
                        ],
                        [
                            -90.93761107366635,
                            29.431944684696646
                        ],
                        [
                            -90.83053532840398,
                            29.43551387620539
                        ],
                        [
                            -90.76272068973782,
                            29.446221450731628
                        ],
                        [
                            -90.70561362559789,
                            29.456929025257864
                        ],
                        [
                            -90.63779898693173,
                            29.456929025257864
                        ],
                        [
                            -90.59496868882678,
                            29.446221450731628
                        ],
                        [
                            -90.51644647563438,
                            29.43551387620539
                        ],
                        [
                            -90.47361617752944,
                            29.442652259222882
                        ],
                        [
                            -90.43792426244198,
                            29.471205791292846
                        ],
                        [
                            -90.41650911338951,
                            29.503328514871555
                        ]
                    ]
                ]
            },
            "properties": {
                "FID": 0,
                "Id": 0
            }
        }
    ]
}